LICENSE
MANIFEST.in
README.md
setup.cfg
setup.py
tap_trustpilot/__init__.py
tap_trustpilot/context.py
tap_trustpilot/http.py
tap_trustpilot/schemas.py
tap_trustpilot/streams.py
tap_trustpilot/transform.py
tap_trustpilot.egg-info/PKG-INFO
tap_trustpilot.egg-info/SOURCES.txt
tap_trustpilot.egg-info/dependency_links.txt
tap_trustpilot.egg-info/entry_points.txt
tap_trustpilot.egg-info/requires.txt
tap_trustpilot.egg-info/top_level.txt
tap_trustpilot/schemas/business_units.json
tap_trustpilot/schemas/consumers.json
tap_trustpilot/schemas/reviews.json